{
  "project_info": {
    "project_number": "145601574664",
    "project_id": "teach-code-app",
    "storage_bucket": "teach-code-app.appspot.com"
  },
  "client": [
    {
      "client_info": {
        "mobilesdk_app_id": "1:145601574664:android:d6603b8364743f13b9debd",
        "android_client_info": {
          "package_name": "com.example.teachcode"
        }
      },
      "oauth_client": [
        {
          "client_id": "145601574664-ufh42mqd5g7i4a4k06bc02vi3immjb6f.apps.googleusercontent.com",
          "client_type": 3
        }
      ],
      "api_key": [
        {
          "current_key": "AIzaSyAvLTfB7rOr231uNz3QqthI88cHyrgBAIw"
        }
      ],
      "services": {
        "appinvite_service": {
          "other_platform_oauth_client": [
            {
              "client_id": "145601574664-ufh42mqd5g7i4a4k06bc02vi3immjb6f.apps.googleusercontent.com",
              "client_type": 3
            }
          ]
        }
      }
    }
  ],
  "configuration_version": "1"
}